ryglfg/__init__.py
ryglfg/__main__.py
ryglfg/auth.py
ryglfg/database.py
ryglfg/globals.py
ryglfg/models.py
ryglfg-3.0.0.dist-info/WHEEL
ryglfg-3.0.0.dist-info/METADATA
ryglfg-3.0.0.dist-info/RECORD
