Metadata-Version: 2.1
Name: ryglfg
Version: 3.0.0
Summary: The "Looking For Group" service of the RYG community
License: AGPL-3.0-or-later
Author: Stefano Pigozzi
Author-email: me@steffo.eu
Requires-Python: >=3.9,<4.0
Classifier: License :: OSI Approved :: GNU Affero General Public License v3 or later (AGPLv3+)
Classifier: Programming Language :: Python :: 3
Classifier: Programming Language :: Python :: 3.9
Requires-Dist: SQLAlchemy (>=1.4.0b3,<2.0.0)
Requires-Dist: fastapi (>=0.63.0,<0.64.0)
Requires-Dist: fastapi-cloudauth (>=0.3.0,<0.4.0)
Requires-Dist: psycopg2 (>=2.8.6,<3.0.0)
Requires-Dist: requests (>=2.25.1,<3.0.0)
Requires-Dist: royalnet (>=6.0.2,<7.0.0)
Requires-Dist: uvicorn (>=0.13.4,<0.14.0)
